Metadata-Version: 2.1
Name: nkf
Version: 1.0.2
Summary: Python Interface to NKF
Home-page: https://github.com/fumiyas/python-nkf
Author: SATOH Fumiyasu
Author-email: fumiyas@osstech.co.jp
License: BSD
